{
  "title": "产业型战略股东与国有企业创新",
  "authors": [
    "蔡贵龙等",
    "产业型战",
    "略股东与",
    "国有企业",
    "创新"
  ],
  "keywords": [
    "产业型战略股东",
    "国有企业",
    "企业创新",
    "经营范围相似度"
  ],
  "abstract": "全面提升国有企业创新能力是国有企业改革深化提升行动的重要 目标，也是加快发展新质生产力的必然要求。本文采用文本分析方法测量法人股 东与上市公司经营范围相似度，识别产业型战略股东，进而探究其对国有企业创 新投入、效率、产出与质量的综合影响。研究发现：引入与公司经营范围相近的产 业型战略股东有助于提升国有企业的创新产出数量；当产业型战略股东的持股比 例更大、持股时间更长以及产业型战略股东为非国有性质时，其对国有企业创新 产出的促进效应更强。机制分析表明：产业型战略股东一方面能更有效地抑制管 理层短视行为，提高国有企业的创新投入；另一方面有助于提升国有企业的资源 协同与整合能力，提高国有企业的创新效率。此外，产业型战略股东不仅有助于 促进国有企业的创新产出数量，也显著促进了国有企业的创新产出质量。本文丰 富了关于国有企业产权改革的研究，揭示了产业型战略股东推进国有企业创新的 机理与治理价值，对于进一步深化国有企业产权改革，提升国有企业创新能力和 实现高质量发展具有重要的政策启示。",
  "language": "zh",
  "methods": [
    "文本分析方法(计算经营范围相似度)",
    "固定效应模型",
    "机制分析"
  ],
  "industries": [
    "国有企业",
    "制造业"
  ],
  "cssci_categories": [
    "管理学",
    "经济学",
    "政治学"
  ],
  "funding": [
    "72472165",
    "72132010"
  ],
  "jel_codes": [
    {
      "code": "L32",
      "confidence": 0.9,
      "source": "inferred_cn"
    },
    {
      "code": "P31",
      "confidence": 0.9,
      "source": "inferred_cn"
    },
    {
      "code": "L60",
      "confidence": 0.9,
      "source": "inferred_cn"
    },
    {
      "code": "L20",
      "confidence": 0.9,
      "source": "inferred_cn"
    },
    {
      "code": "D21",
      "confidence": 0.9,
      "source": "inferred_cn"
    },
    {
      "code": "L00",
      "confidence": 0.58,
      "source": "inferred_cn"
    },
    {
      "code": "M10",
      "confidence": 0.58,
      "source": "inferred_cn"
    },
    {
      "code": "L10",
      "confidence": 0.58,
      "source": "inferred_cn"
    }
  ]
}