{
  "title": "农户增收的中国经验：",
  "authors": [
    "农户增收",
    "的中国经"
  ],
  "keywords": [
    "小额信贷",
    "农户增收",
    "农村致富带头人",
    "中国特色金融发展之路"
  ],
  "abstract": "中国小额信贷的广泛积极成效与国际大量负面证据形成反差，这 蕴含着独特的“中国经验”。基于长期驻村观察和调研，本文提出农村致富带头人 制度与小额信贷的协同机制：信贷帮助农户跨越资金门槛，而致富带头人通过 “传、帮、带”提升其生产经营能力，共同形成“1+1>2”的效果。通过构建包含人力 资本外溢与信贷约束的农业经济增长模型阐释作用机制，并利用某典型欠发达县 近2 万户脱贫监测户的独特微观跟踪数据进行实证检验，辅以某地级市和全国层 面的数据。研究发现，致富带头人帮扶能够显著强化小额信贷的增收效果，提升 增收的可持续性，并且“信贷贴息+致富带头人选育”的政策组合能够大幅提升财 政资金使用效率。这一模式是中国特色金融发展之路的重要实践，为全球普惠金 融发展、提高财政资金效率、防控小额信贷风险提供了启示与借鉴。",
  "language": "zh",
  "methods": [
    "理论建模：包含人力资本外溢与信贷约束的农业经济增长模型",
    "实地调研：长期驻村观察",
    "实证分析：使用微观跟踪数据进行统计分析"
  ],
  "industries": [
    "农业",
    "农村金融业"
  ],
  "cssci_categories": [
    "管理学",
    "经济学",
    "政治学"
  ],
  "funding": [
    "72573130",
    "24ZDA019"
  ],
  "jel_codes": [
    {
      "code": "Q12",
      "confidence": 0.9,
      "source": "inferred_cn"
    },
    {
      "code": "Q10",
      "confidence": 0.77,
      "source": "inferred_cn"
    },
    {
      "code": "D13",
      "confidence": 0.58,
      "source": "inferred_cn"
    },
    {
      "code": "G20",
      "confidence": 0.55,
      "source": "inferred_cn"
    },
    {
      "code": "G21",
      "confidence": 0.5,
      "source": "inferred_cn"
    },
    {
      "code": "R20",
      "confidence": 0.38,
      "source": "inferred_cn"
    },
    {
      "code": "G00",
      "confidence": 0.38,
      "source": "inferred_cn"
    },
    {
      "code": "G32",
      "confidence": 0.33,
      "source": "inferred_cn"
    }
  ]
}